kidibox
