Metadata-Version: 1.1
Name: kidibox-py
Version: 0.1.3
Summary: A Python library to interact with kidibox-api
Home-page: https://github.com/kidibox/kidibox-py
Author: Cecile Tonglet
Author-email: UNKNOWN
License: MIT
Platform: UNKNOWN
Classifier: Development Status :: 1 - Planning
Classifier: Intended Audience :: Developers
Classifier: Natural Language :: English
Classifier: License :: OSI Approved :: MIT License
Classifier: Programming Language :: Python
Classifier: Programming Language :: Python :: 2.7
Classifier: Programming Language :: Python :: 3
Classifier: Programming Language :: Python :: 3.3
Classifier: Programming Language :: Python :: 3.4
Classifier: Programming Language :: Python :: 3.5
